{
    "Author": "Yoru Shokohime",
    "Name": "Quartermaster",
    "InternalName": "Quartermaster",
    "Punchline": "FFXIV Economy Intelligence Engine — profit alerts, market analysis, and IPC orchestration.",
    "Description": "Consolidates market, crafting, retainer, and submarine profit data into one always-available dashboard. Evaluates profitability continuously against a user-defined watchlist and emits actionable alerts. Orchestrates actions across other Dalamud plugins (Artisan, AutoRetainer, GatherBuddyReborn) via IPC — always with user approval.",
    "AssemblyVersion": "0.4.0.0",
    "ApplicableVersion": "any",
    "DalamudApiLevel": 14,
    "IconUrl": "https://raw.githubusercontent.com/YelenaTor/QIE/master/Resources/Icons/icon.png",
    "LoadRequiredState": 0,
    "LoadSync": false,
    "LoadPriority": 0,
    "Tags": [
        "economy",
        "market",
        "crafting",
        "retainer",
        "submarine",
        "profit"
    ],
    "Changelog": "v0.4.8\n- Added QIE plugin icon\n- Fixed crash on load (Una.Drawing async init)\n- Fixed ImGui namespace for Dalamud API 14 (ImGuiNET → Dalamud.Bindings.ImGui)\n- Fixed Una.Drawing API compatibility (OnMouseUp, QuerySelectorAll)\n- Added GlobalUsings.cs for Dalamud SDK\n- Added Resources directory for icons, fonts, textures"
}